llmprogram/LLMProgram.py
llmprogram/__init__.py
llmprogram/analytics.py
llmprogram/cli.py
llmprogram/web.py
llmprogram-0.1.2.dist-info/LICENSE
llmprogram-0.1.2.dist-info/METADATA
llmprogram-0.1.2.dist-info/WHEEL
llmprogram-0.1.2.dist-info/entry_points.txt
llmprogram-0.1.2.dist-info/RECORD
