Metadata-Version: 2.3
Name: llmprogram
Version: 0.1.2
Summary: A Python package for creating and running LLM programs.
License: MIT
Author: Dipankar Sarkar
Author-email: me@dipankar.name
Requires-Python: >=3.9
Classifier: License :: OSI Approved :: MIT License
Classifier: Programming Language :: Python :: 3
Classifier: Programming Language :: Python :: 3.9
Classifier: Programming Language :: Python :: 3.10
Classifier: Programming Language :: Python :: 3.11
Classifier: Programming Language :: Python :: 3.12
Classifier: Programming Language :: Python :: 3.13
Requires-Dist: aiosqlite (>=0.21.0,<0.22.0)
Requires-Dist: duckdb (>=0.9.0,<0.10.0)
Requires-Dist: fastapi (>=0.104.0,<0.105.0)
Requires-Dist: jinja2 (>=3.1.6,<4.0.0)
Requires-Dist: jsonschema (>=4.25.0,<5.0.0)
Requires-Dist: openai (>=1.99.7,<2.0.0)
Requires-Dist: pydantic (>=2.0.0,<3.0.0)
Requires-Dist: pyyaml (>=6.0.2,<7.0.0)
Requires-Dist: redis (>=6.4.0,<7.0.0)
Requires-Dist: uvicorn (>=0.23.0,<0.24.0)
